django_triflesoft_localization-0.7.1702191535.dist-info/DESCRIPTION.rst
django_triflesoft_localization-0.7.1702191535.dist-info/METADATA
django_triflesoft_localization-0.7.1702191535.dist-info/RECORD
django_triflesoft_localization-0.7.1702191535.dist-info/WHEEL
django_triflesoft_localization-0.7.1702191535.dist-info/metadata.json
django_triflesoft_localization-0.7.1702191535.dist-info/top_level.txt
localization/__init__.py
localization/admin.py
localization/models.py
