Metadata-Version: 2.0
Name: django-triflesoft-localization
Version: 0.7.1702191535
Summary: Django alternative localization by TrifleSoft
Home-page: https://bitbucket.org/triflesoft/django-localization
Author: TrifleSoft LLC
Author-email: support@triflesoft.org
License: BSD
Keywords: django localization triflesoft
Platform: UNKNOWN
Classifier: Development Status :: 5 - Production/Stable
Classifier: Environment :: No Input/Output (Daemon)
Classifier: Framework :: Django
Classifier: Framework :: Django :: 1.10
Classifier: Intended Audience :: Developers
Classifier: License :: OSI Approved :: BSD License
Classifier: Operating System :: POSIX :: Linux
Classifier: Programming Language :: Python :: 3 :: Only
Classifier: Programming Language :: Python :: 3.4
Classifier: Programming Language :: Python :: 3.5
Classifier: Topic :: Software Development :: Localization
Requires-Dist: django
